isalmd/LMD.py
isalmd/__init__.py
isalmd-0.0.2.dist-info/DESCRIPTION.rst
isalmd-0.0.2.dist-info/METADATA
isalmd-0.0.2.dist-info/RECORD
isalmd-0.0.2.dist-info/WHEEL
isalmd-0.0.2.dist-info/metadata.json
isalmd-0.0.2.dist-info/top_level.txt
