Metadata-Version: 2.0
Name: isalmd
Version: 0.0.2
Summary: LMD filereader reads LMD files
Home-page: https://bitbucket.org/hirschbeutel/isalmd
Author: hirschbeutel
Author-email: hirschbeutel@gmail.com
License: LGPL
Platform: UNKNOWN
